README.md
pyproject.toml
setup.py
src/AutoDD.py
src/__init__.py
src/fast_yahoo.py
src/AutoDD.egg-info/PKG-INFO
src/AutoDD.egg-info/SOURCES.txt
src/AutoDD.egg-info/dependency_links.txt
src/AutoDD.egg-info/entry_points.txt
src/AutoDD.egg-info/requires.txt
src/AutoDD.egg-info/top_level.txt