Metadata-Version: 2.1
Name: AutoDD
Version: 2.1.5
Home-page: https://github.com/DylanAlloy/AutoDD_Rev2
